fitness_tools/__init__.py
fitness_tools/composition/__init__.py
fitness_tools/composition/bodyfat.py
fitness_tools/exercise/__init__.py
fitness_tools/exercise/rm_estimator.py
fitness_tools/meals/__init__.py
fitness_tools/meals/meal_maker.py
fitness_tools-0.1.1.dist-info/METADATA
fitness_tools-0.1.1.dist-info/RECORD
fitness_tools-0.1.1.dist-info/WHEEL
fitness_tools-0.1.1.dist-info/top_level.txt
tests/__init__.py
tests/test_bodyfat_calculator.py
tests/test_meal_maker.py
tests/test_rm_calculator.py
