Metadata-Version: 2.1
Name: fitness-tools
Version: 0.1.1
Summary: Healthy Lifestyles With Python
Home-page: https://github.com/Maverick-Coders/Fitness-Tools
Author: Maverick Coders
Author-email: maverickcoders@pm.me
License: UNKNOWN
Keywords: health,wellness,fitness,exercise,nutrition
Platform: UNKNOWN
Classifier: Programming Language :: Python :: 3
Classifier: License :: OSI Approved :: Apache Software License
Classifier: Operating System :: OS Independent
